README.rst
setup.py
peek_plugin_tutorial/__init__.py
peek_plugin_tutorial/plugin_package.json
peek_plugin_tutorial.egg-info/PKG-INFO
peek_plugin_tutorial.egg-info/SOURCES.txt
peek_plugin_tutorial.egg-info/dependency_links.txt
peek_plugin_tutorial.egg-info/requires.txt
peek_plugin_tutorial.egg-info/top_level.txt
peek_plugin_tutorial/_private/PluginNames.py
peek_plugin_tutorial/_private/__init__.py
peek_plugin_tutorial/_private/alembic.ini
peek_plugin_tutorial/_private/admin-app/tutorial.component.html
peek_plugin_tutorial/_private/admin-app/tutorial.component.ts
peek_plugin_tutorial/_private/admin-app/tutorial.module.ts
peek_plugin_tutorial/_private/admin-app/edit-setting-table/edit.component.html
peek_plugin_tutorial/_private/admin-app/edit-setting-table/edit.component.ts
peek_plugin_tutorial/_private/admin-app/edit-string-int-table/edit.component.html
peek_plugin_tutorial/_private/admin-app/edit-string-int-table/edit.component.ts
peek_plugin_tutorial/_private/agent/AgentEntryHook.py
peek_plugin_tutorial/_private/agent/AgentToServerRpcCallExample.py
peek_plugin_tutorial/_private/agent/RpcForServer.py
peek_plugin_tutorial/_private/agent/__init__.py
peek_plugin_tutorial/_private/alembic/__init__.py
peek_plugin_tutorial/_private/alembic/env.py
peek_plugin_tutorial/_private/alembic/script.py.mako
peek_plugin_tutorial/_private/alembic/versions/0b12f40fadba_added_stringint_table.py
peek_plugin_tutorial/_private/alembic/versions/450e040742f8_added_setting_table.py
peek_plugin_tutorial/_private/alembic/versions/__init__.py
peek_plugin_tutorial/_private/client/ClientEntryHook.py
peek_plugin_tutorial/_private/client/DeviceTupleDataObservableProxy.py
peek_plugin_tutorial/_private/client/DeviceTupleProcessorActionProxy.py
peek_plugin_tutorial/_private/client/__init__.py
peek_plugin_tutorial/_private/mobile-app/tutorial.component.mweb.html
peek_plugin_tutorial/_private/mobile-app/tutorial.component.ns.html
peek_plugin_tutorial/_private/mobile-app/tutorial.component.ts
peek_plugin_tutorial/_private/mobile-app/tutorial.module.ts
peek_plugin_tutorial/_private/mobile-app/string-int/string-int.component.mweb.html
peek_plugin_tutorial/_private/mobile-app/string-int/string-int.component.ns.html
