Metadata-Version: 1.1
Name: peek-plugin-tutorial
Version: 1.3.0
Summary: Peek Plugin Tutorial - My first enhancement.
Home-page: https://bitbucket.org/synerty/peek-plugin-tutorial
Author: Synerty
Author-email: contact@synerty.com
License: UNKNOWN
Download-URL: https://bitbucket.org/synerty/peek-plugin-tutorial/get/1.3.0.zip
Keywords: Peek,Python,Platform,synerty
Platform: UNKNOWN
